.coveragerc
.coveragerc-pypy
.landscape.yml
.pylintrc
.readthedocs.yml
AUTHORS
CHANGES.rst
CONTRIBUTING.rst
LICENSE
MANIFEST.in
NOTICE
README.rst
TODO
_setupares.py
_setuplibev.py
_setuputils.py
appveyor.yml
dev-requirements.txt
pyproject.toml
setup.cfg
setup.py
tox.ini
.github/ISSUE_TEMPLATE.md
appveyor/install.ps1
appveyor/run_with_env.cmd
benchmarks/bench_dns_resolver.py
benchmarks/bench_get_memory.py
benchmarks/bench_hub.py
benchmarks/bench_local.py
benchmarks/bench_pool.py
benchmarks/bench_queue.py
benchmarks/bench_sendall.py
benchmarks/bench_sleep0.py
benchmarks/bench_socket.py
benchmarks/bench_spawn.py
benchmarks/bench_subprocess.py
benchmarks/bench_threadpool.py
benchmarks/bench_tracer.py
benchmarks/micro.sh
benchmarks/micro_greenlet_link.sh
benchmarks/micro_run_callback.sh
benchmarks/micro_semaphore.sh
benchmarks/micro_sleep.sh
deps/README.rst
deps/cares-make.patch
deps/cares-win32.patch
deps/libuv-1.38-static-assert.patch
deps/c-ares/AUTHORS
deps/c-ares/CHANGES
deps/c-ares/INSTALL.md
deps/c-ares/LICENSE.md
deps/c-ares/Makefile.Watcom
deps/c-ares/Makefile.am
deps/c-ares/Makefile.dj
deps/c-ares/Makefile.in
deps/c-ares/Makefile.m32
deps/c-ares/Makefile.msvc
deps/c-ares/Makefile.netware
deps/c-ares/NEWS
deps/c-ares/README.cares
deps/c-ares/README.md
deps/c-ares/README.msvc
deps/c-ares/RELEASE-NOTES
deps/c-ares/TODO
deps/c-ares/acinclude.m4
deps/c-ares/aclocal.m4
deps/c-ares/buildconf
deps/c-ares/compile
deps/c-ares/config.guess
deps/c-ares/config.sub
deps/c-ares/configure
deps/c-ares/configure.ac
deps/c-ares/depcomp
deps/c-ares/get_ver.awk
deps/c-ares/install-sh
deps/c-ares/libcares.pc.in
deps/c-ares/ltmain.sh
deps/c-ares/missing
deps/c-ares/msvc_ver.inc
deps/c-ares/include/CMakeLists.txt
deps/c-ares/include/Makefile.am
deps/c-ares/include/Makefile.in
deps/c-ares/include/ares.h
deps/c-ares/include/ares_build.h
deps/c-ares/include/ares_build.h.cmake
deps/c-ares/include/ares_build.h.dist
deps/c-ares/include/ares_build.h.in
deps/c-ares/include/ares_dns.h
src/gevent_lbh.egg-info/PKG-INFO
src/gevent_lbh.egg-info/SOURCES.txt
src/gevent_lbh.egg-info/dependency_links.txt
src/gevent_lbh.egg-info/entry_points.txt
src/gevent_lbh.egg-info/not-zip-safe
src/gevent_lbh.egg-info/requires.txt
src/gevent_lbh.egg-info/top_level.txt
