Metadata-Version: 2.1
Name: gevent-lbh
Version: 21.1.3.dev0
Summary: Coroutine-based network library
Home-page: http://www.gevent.org/
Author: Denis Bilenko
Author-email: denis.bilenko@gmail.com
Maintainer: Jason Madden
Maintainer-email: jason@nextthought.com
License: MIT
Project-URL: Bug Tracker, https://github.com/gevent/gevent/issues
Project-URL: Documentation, http://www.gevent.org
Project-URL: Source Code, https://github.com/gevent/gevent/
Keywords: greenlet coroutine cooperative multitasking light threads monkey
Platform: UNKNOWN
Classifier: License :: OSI Approved :: MIT License
Classifier: Programming Language :: Python :: 2.7
Classifier: Programming Language :: Python :: 3.4
Classifier: Programming Language :: Python :: 3.5
Classifier: Programming Language :: Python :: 3.6
Classifier: Programming Language :: Python :: 3.7
Classifier: Programming Language :: Python :: 3.8
Classifier: Programming Language :: Python :: 3.9
Classifier: Programming Language :: Python :: Implementation :: CPython
Classifier: Programming Language :: Python :: Implementation :: PyPy
Classifier: Operating System :: MacOS :: MacOS X
Classifier: Operating System :: POSIX
Classifier: Operating System :: Microsoft :: Windows
Classifier: Topic :: Internet
Classifier: Topic :: Software Development :: Libraries :: Python Modules
Classifier: Intended Audience :: Developers
Classifier: Development Status :: 4 - Beta
Requires-Python: >=2.7,!=3.0.*,!=3.1.*,!=3.2.*,!=3.3.*,!=3.4.*
Provides-Extra: monitor
Provides-Extra: docs
Provides-Extra: recommended
Provides-Extra: test
Provides-Extra: dnspython
Provides-Extra: events
